my_module/__init__.py
my_module/luaslingkar.py
lingkar33423309-0.0.1.dist-info/LICENSE
lingkar33423309-0.0.1.dist-info/METADATA
lingkar33423309-0.0.1.dist-info/WHEEL
lingkar33423309-0.0.1.dist-info/top_level.txt
lingkar33423309-0.0.1.dist-info/RECORD
